ghbot/__init__.py
ghbot/bot.py
ghbot/cli.py
ghbot/exception/__init__.py
ghbot-0.6.0.dist-info/LICENSE.txt
ghbot-0.6.0.dist-info/METADATA
ghbot-0.6.0.dist-info/WHEEL
ghbot-0.6.0.dist-info/top_level.txt
ghbot-0.6.0.dist-info/RECORD
