Metadata-Version: 2.1
Name: ghbot
Version: 0.6.0
Summary: Github Follow Bot to Get More Followers in Python.
Home-page: https://github.com/clivern/ghbot/
Author: Clivern
Author-email: hello@clivern.com
License: MIT
Project-URL: Documentation, https://github.com/clivern/ghbot/
Project-URL: Source, https://github.com/clivern/ghbot/
Project-URL: Changelog, https://github.com/clivern/ghbot/blob/main/CHANGELOG.rst
Project-URL: Tracker, https://github.com/clivern/ghbot/issues
Project-URL: Download, https://pypi.org/project/ghbot/#files
Platform: any
Classifier: Development Status :: 5 - Production/Stable
Classifier: Programming Language :: Python
Classifier: License :: OSI Approved :: MIT License
License-File: LICENSE.txt
Requires-Dist: PyGithub
Requires-Dist: importlib-metadata ; python_version < "3.8"
